{
  "id": "kb_hooks_20260315_161333_c8ecdc",
  "category": "hooks",
  "subcategory": "",
  "name": "奇幻衝突開場",
  "name_en": "Fantasy Conflict Opening",
  "description": "以九天玄女在天庭打麻將贏錢的荒誕場景開場，瞬間建立角色的強大與不羈，隨即被閻王偷襲貶下凡間，製造巨大落差感，觀眾既好奇她的來歷又想看她如何翻盤。",
  "tags": [
    "開場",
    "穿越",
    "讀心術",
    "先婚後愛",
    "霸總",
    "醜女逆襲",
    "九天玄女",
    "豪門恩怨",
    "手撕小三",
    "身體互換",
    "私生子復仇",
    "原生家庭",
    "打臉復仇",
    "甜寵",
    "爽文",
    "仙俠都市"
  ],
  "examples": [
    {
      "drama_title": "Witch transmigrated to ugly wife, fam hears her inner voice! rise all the way, become CEO's fave!",
      "video_id": "eXSpqKAk8ik",
      "excerpt": "You'd better have something better than my pure hand, big monotone, consecutive Kong self-drawn to win all the king of hell's money... lady of the nine heavens, don't blame me. The entire heavenly court and underworld jointly petitioned to send you on this tribulation.",
      "context": "開場"
    }
  ],
  "effectiveness_score": 7,
  "usage_count": 0,
  "created_at": "2026-03-15 16:13:33",
  "updated_at": "2026-03-15 16:13:33"
}