{
  "id": "kb_hooks_20260315_155212_e8a4de",
  "category": "hooks",
  "subcategory": "",
  "name": "陰謀揭露鉤子",
  "name_en": "Conspiracy Reveal Hook",
  "description": "在女主準備喪事的同時，切換到反派視角揭露假死陰謀，讓觀眾同時知道雙方的底牌，形成戲劇性張力。",
  "tags": [
    "開場後段",
    "重生復仇",
    "古裝宅鬥",
    "先婚後愛",
    "打臉爽文",
    "惡婆婆",
    "假死陰謀",
    "嫁妝爭奪",
    "智鬥渣男",
    "王爺守護",
    "封棺名場面",
    "族規休妻",
    "養子背叛",
    "白蓮花小三",
    "女主逆襲",
    "皇權加持"
  ],
  "examples": [
    {
      "drama_title": "被假死丈夫和養子聯手滅門？重生歸來她釘棺拒守寡，智鬥渣男復仇，竟陷先婚後愛！《錯嫁君》#重生 #短剧 #最火短剧推荐 #minidrama #古装",
      "video_id": "IygzCYGFVCI",
      "excerpt": "哈哈，我兒子真聰明，竟然假死逃走。真是個絕妙的主意。公爵府崇尚智慧和美德，就用貞潔的名義留住陸寧安吧。她的嫁妝和公爵府的錢財可不是我們所有的，哈哈。",
      "context": "開場後段"
    }
  ],
  "effectiveness_score": 7,
  "usage_count": 0,
  "created_at": "2026-03-15 15:52:12",
  "updated_at": "2026-03-15 15:52:12"
}