{
  "id": "kb_tension_actions_20260315_160457_b53b91",
  "category": "tension_actions",
  "subcategory": "",
  "name": "戒指掉落（公開出醜危機）",
  "name_en": "Ring drop (public embarrassment crisis)",
  "description": "婚禮上戒指掉落不僅是物理動作，更是「失明秘密即將暴露」的視覺化表達，所有賓客的注視放大了緊張感。",
  "tags": [
    "安靜的婚禮現場，金屬戒指落地的清脆聲響，所有人的目光聚焦",
    "替嫁",
    "雙胞胎",
    "盲人CEO",
    "契約婚姻",
    "假夫妻真動心",
    "身份隱藏",
    "豪門陰謀",
    "隱藏實力女主",
    "Victoria獨立調香師",
    "兄弟鬩牆",
    "復仇逆襲",
    "身份揭露",
    "車禍陰謀",
    "重新求婚",
    "忠僕助攻"
  ],
  "examples": [
    {
      "drama_title": "love drama \"I was tricked into marrying a blind CEO I didn't know\" HD FULL, CEO,ENGSUB,  Episodes",
      "video_id": "vPaySGfWlD4",
      "excerpt": "The ring. It drops. Told you Christian is blind. / What's going on with the ring? You missed completely.",
      "context": "安靜的婚禮現場，金屬戒指落地的清脆聲響，所有人的目光聚焦"
    }
  ],
  "effectiveness_score": 7,
  "usage_count": 0,
  "created_at": "2026-03-15 16:04:57",
  "updated_at": "2026-03-15 16:04:57"
}