{
  "id": "kb_pacing_20260315_155922_467d5c",
  "category": "pacing",
  "subcategory": "",
  "name": "快節奏高密度衝突，前慢後爆型",
  "name_en": "",
  "description": "開場高壓建立同情→短暫蓄力佈局→中段密集交鋒螺旋上升→高潮全面碾壓爆發→結尾甜寵收束",
  "tags": [
    "重生復仇",
    "大女主逆襲",
    "姐妹對決",
    "豪門恩怨",
    "霸總甜寵",
    "追妻火葬場",
    "灰姑娘翻身",
    "當眾打臉",
    "身份反轉",
    "心機白蓮花",
    "家族偏心",
    "小說改編"
  ],
  "examples": [
    {
      "drama_title": "💔Reborn as unloved daughter, I crush scheming sister!#chinesedrama",
      "video_id": "Yf3BuJBSAS8",
      "excerpt": "（字幕資料不足，基於標題和描述推斷）頻道描述 'focusing on sweet pets, time travel, and rebirth' 暗示節奏在復仇爽感與甜寵調劑之間交替，時長 PT6180S（約103分鐘）支撐多幕漸進式節奏",
      "context": "重生覺醒：女主意識到自己重生，決心改變命運; 第一次小勝：女主首次識破姐姐陰謀，小規模反擊成功; 中段危機：姐姐加大力度反撲，女主暫時陷入困境; 男主傾斜：男主開始注意到女主的真實魅力; 真相揭露高潮：姐姐所有陰謀被當眾拆穿; 終極碾壓：女主全面翻盤，獲得地位、愛情、家族認可"
    }
  ],
  "effectiveness_score": 6,
  "usage_count": 0,
  "created_at": "2026-03-15 15:59:22",
  "updated_at": "2026-03-15 15:59:22"
}