{
  "id": "kb_ending_hooks_20260315_152902_7b2203",
  "category": "ending_hooks",
  "subcategory": "",
  "name": "懸念型結尾鉤子",
  "name_en": "Suspense Ending Hook",
  "description": "每集結尾在關鍵衝突或揭露的臨界點切斷，讓觀眾必須看下一集才能知道結果。短劇的159分鐘時長意味著多集連載，每集結尾都需要強力鉤子留住觀眾。",
  "tags": [
    "每集最後幾秒/關鍵台詞說到一半時切斷",
    "復仇婚姻",
    "霸道護妻",
    "家族仇恨",
    "仇敵變愛人",
    "假結婚真動心",
    "豪門恩怨",
    "逆襲翻盤",
    "先婚後愛",
    "禁忌之戀",
    "甜寵爽文",
    "身份反轉",
    "強強聯手"
  ],
  "examples": [
    {
      "drama_title": "THE ULTIMATE REVENGE MARRIGE: I WED MY FAMILY'S ENEMY! ♟️His Only Rule: \"No One Touches My Wife.❤️‍🔥",
      "video_id": "kEFShWq9Wh0",
      "excerpt": "（字幕資料不足，基於描述推斷）'Plot twists'和'no dull moments'暗示每集結尾都有懸念設計。",
      "context": "每集最後幾秒/關鍵台詞說到一半時切斷"
    }
  ],
  "effectiveness_score": 7,
  "usage_count": 0,
  "created_at": "2026-03-15 15:29:02",
  "updated_at": "2026-03-15 15:29:02"
}