{
  "id": "kb_elements_20260315_155815_59a77f",
  "category": "elements",
  "subcategory": "關係",
  "name": "先婚後愛（契約婚姻→真情相許）",
  "name_en": "Marriage Before Love (Contract Marriage to True Love)",
  "description": "女主嫁給昏迷皇叔本質是策略性婚姻——借皇叔之名避開太子、獲得保護傘。但隨著皇叔甦醒、相處漸深，策略變成真心。衝突核心在於：當皇叔得知女主最初的『功利動機』時如何面對？",
  "tags": [
    "關係",
    "重生復仇",
    "古裝宮鬥",
    "先婚後愛",
    "太子虐殺",
    "皇叔甦醒",
    "隱藏實力",
    "女主逆襲",
    "打臉爽劇",
    "前世今生",
    "權謀博弈",
    "甜寵虐戀",
    "廢物皇叔真大佬",
    "主動請嫁"
  ],
  "examples": [
    {
      "drama_title": "上輩子被太子虐死，重生後我主動嫁給昏迷的皇叔。",
      "video_id": "uSpaeczjsdY",
      "excerpt": "（字幕資料不足，基於標題推斷）『主動嫁給昏迷的皇叔』——這是一場帶有明確目的性的婚姻，為先婚後愛奠定基礎。",
      "context": "女主嫁給昏迷皇叔本質是策略性婚姻——借皇叔之名避開太子、獲得保護傘。但隨著皇叔甦醒、相處漸深，策略變成真心。衝突核心在於：當皇叔得知女主最初的『功利動機』時如何面對？"
    }
  ],
  "effectiveness_score": 6,
  "usage_count": 0,
  "created_at": "2026-03-15 15:58:15",
  "updated_at": "2026-03-15 15:58:15"
}