{
  "id": "kb_visual_scenes_20260315_153614_e588d0",
  "category": "visual_scenes",
  "subcategory": "",
  "name": "CEO病房甦醒場景",
  "name_en": "CEO Hospital Awakening Scene",
  "description": "女主用神力救醒昏迷CEO的場景，是愛情線的起點。病房的封閉空間增強親密感，甦醒瞬間的四目相對是經典的視覺定格。",
  "tags": [
    "生死之間的緊張氛圍與甦醒後的溫情形成反差，奠定兩人命運聯結",
    "重生復仇",
    "神力覺醒",
    "身份互換",
    "豪門恩怨",
    "一夜破產",
    "霸總甜寵",
    "扮豬吃老虎",
    "棄女逆襲",
    "知恩圖報",
    "古代女神轉世",
    "打臉爽劇",
    "家族權鬥",
    "rags to riches",
    "hidden identity",
    "divine power"
  ],
  "examples": [
    {
      "drama_title": "Revenge of the Reborn Heiress: Disowned, I Awakened My Divine Power & Bankrupted My Family Overnight",
      "video_id": "JbwJbPjfkA8",
      "excerpt": "a handsome CEO she saved from a coma",
      "context": "生死之間的緊張氛圍與甦醒後的溫情形成反差，奠定兩人命運聯結"
    }
  ],
  "effectiveness_score": 7,
  "usage_count": 0,
  "created_at": "2026-03-15 15:36:14",
  "updated_at": "2026-03-15 15:36:14"
}