{
  "id": "kb_visual_scenes_20260315_160420_8e63f1",
  "category": "visual_scenes",
  "subcategory": "",
  "name": "斷臂贖罪——男主自殘跪求",
  "name_en": "Self-Mutilation Atonement — Male Lead Kneeling",
  "description": "曾經不可一世的王爺自斷手臂出現在女主面前，權力的徹底反轉以最暴烈的方式呈現",
  "tags": [
    "昔日的掌控者成為乞求者，肉體的殘缺象徵他對過去行為的不可挽回的認知",
    "影衛",
    "滅門遺孤",
    "練習靶子",
    "白月光vs真愛",
    "虐戀情深",
    "身份揭露",
    "復仇逆襲",
    "先虐後甜",
    "男二上位",
    "斷臂贖罪",
    "禁忌之戀",
    "藥血血脈",
    "古裝權謀",
    "女主覺醒",
    "階級壓迫",
    "三角關係"
  ],
  "examples": [
    {
      "drama_title": "新劇搶先看【君心照月白】他曾在她最動情時，涼薄告知要娶白月光。當她被正妃當作玩物、被他像送禮物般推出……心死孤女徹底消失。寧王瘋魔悔恨——她已被帝王視若珍寶。",
      "video_id": "LU12j_H1eRw",
      "excerpt": "伊森王子……他自己斷了手臂。他在入口處……我來贖罪……我應該刺穿自己的胸膛。但我不忍心死。我害怕死。我再也見不到你了",
      "context": "昔日的掌控者成為乞求者，肉體的殘缺象徵他對過去行為的不可挽回的認知"
    }
  ],
  "effectiveness_score": 7,
  "usage_count": 0,
  "created_at": "2026-03-15 16:04:20",
  "updated_at": "2026-03-15 16:04:20"
}