{
  "id": "kb_visual_scenes_20260315_153812_c572e9",
  "category": "visual_scenes",
  "subcategory": "",
  "name": "婚禮被毀 / 婚禮反轉",
  "name_en": "Wedding Disruption / Wedding Reversal Scene",
  "description": "婚禮場景本身具有強烈的視覺符號性——白色婚紗、紅色喜慶裝飾、賓客盛裝。在這個美好場景中發生背叛，形成視覺與情節的巨大反差。女主身穿婚紗微笑離場的畫面極具衝擊力。",
  "tags": [
    "婚禮的神聖象徵與背叛行為的極致反差；女主華服出場卻被當眾拋棄的視覺壓迫感；微笑離場時的優雅與屈辱處境的對比",
    "婚禮背叛",
    "CEO短劇",
    "女主逆襲",
    "身份反轉",
    "微笑離場",
    "全場震驚",
    "情婦上位",
    "爽文復仇",
    "豪門恩怨",
    "先婚後愛反轉",
    "隱忍女主",
    "打臉反派",
    "都市甜虐",
    "快節奏短劇",
    "英語配音中劇"
  ],
  "examples": [
    {
      "drama_title": "Wedding day, but CEO registered marriage with his mistress, Girl left smiling, everyone stunned！",
      "video_id": "xbw0jjruAno",
      "excerpt": "Wedding day, but CEO registered marriage with his mistress, Girl left smiling, everyone stunned！",
      "context": "婚禮的神聖象徵與背叛行為的極致反差；女主華服出場卻被當眾拋棄的視覺壓迫感；微笑離場時的優雅與屈辱處境的對比"
    }
  ],
  "effectiveness_score": 7,
  "usage_count": 0,
  "created_at": "2026-03-15 15:38:12",
  "updated_at": "2026-03-15 15:38:12"
}