{
  "id": "kb_payoffs_20260315_155010_398517",
  "category": "payoffs",
  "subcategory": "",
  "name": "權力徹底翻轉（奪取董事長之位）",
  "name_en": "Complete power reversal (seizing chairmanship)",
  "description": "從被嘲笑的前科犯到掌控整個家族企業，女主完成了從谷底到巔峰的完整逆襲弧線。父親被自己一手培養的高管集體拋棄，權力的諷刺性轉移帶來極大的戲劇快感。",
  "tags": [
    "爽快/震驚",
    "豪門復仇",
    "真假千金",
    "替人頂罪",
    "遺產爭奪",
    "白蓮花反派",
    "集體背叛",
    "隱忍逆襲",
    "打臉爽文",
    "身份反轉",
    "女性復仇",
    "家族企業",
    "繼承權鬥爭",
    "偏心父母",
    "以退為進",
    "終極反轉結局",
    "精神病院懲罰",
    "公開羞辱",
    "遺囑條款",
    "冤獄出獄",
    "多角色群像"
  ],
  "examples": [
    {
      "drama_title": "【ENG DUB】From Convict to Heiress: The Real Daughter's Revenge",
      "video_id": "3EZ75VoTRAI",
      "excerpt": "Bought a meeting to vote on electing Miss Fu as a new chairwoman. ... How dare you betray me? ... If it weren't for Miss Fu, we'd never have gotten our chance.",
      "context": "爽快/震驚"
    }
  ],
  "effectiveness_score": 7,
  "usage_count": 0,
  "created_at": "2026-03-15 15:50:10",
  "updated_at": "2026-03-15 15:50:10"
}