{
  "id": "kb_elements_20260315_162047_74ae1a",
  "category": "elements",
  "subcategory": "人設",
  "name": "穿越智謀型男主（金手指型贅婿）",
  "name_en": "Transmigrated Strategist Protagonist (Cheat-powered Son-in-law)",
  "description": "擁有現代知識和超越時代的見識，被困在古代最卑微的贅婿身份中。核心吸引力在於'明珠蒙塵'的代入感——觀眾知道他有多強，卻看著他被低估，積累的憤懣最終轉化為爆發時的爽感。'智斗'而非'武鬥'定位了這個角色靠腦子而非蠻力取勝。",
  "tags": [
    "人設",
    "穿越",
    "贅婿逆襲",
    "男頻爽文",
    "古裝權謀",
    "智鬥",
    "女帝",
    "寵臣",
    "打臉復仇",
    "身份翻轉",
    "降維打擊",
    "京都朝堂",
    "從卑微到巔峰",
    "未婚妻後悔",
    "王者歸來",
    "殺伐果斷"
  ],
  "examples": [
    {
      "drama_title": "💥完整版：穿越成小小赘婿？看我智斗京都，终成女帝麾下第一宠臣！#youtubeshorts  #drama #最新短劇全集",
      "video_id": "PSWhke53Ls4",
      "excerpt": "（字幕資料不足，基於標題推斷）'穿越成小小赘婿'——穿越者身份確立；'智斗京都'——以智謀為核心能力",
      "context": "擁有現代知識和超越時代的見識，被困在古代最卑微的贅婿身份中。核心吸引力在於'明珠蒙塵'的代入感——觀眾知道他有多強，卻看著他被低估，積累的憤懣最終轉化為爆發時的爽感。'智斗'而非'武鬥'定位了這個角色靠腦子而非蠻力取勝。"
    }
  ],
  "effectiveness_score": 6,
  "usage_count": 0,
  "created_at": "2026-03-15 16:20:47",
  "updated_at": "2026-03-15 16:20:47"
}