{
  "id": "kb_elements_20260315_155212_733a36",
  "category": "elements",
  "subcategory": "關係",
  "name": "童年恩情×成年守護（先婚後愛伏線）",
  "name_en": "Childhood Favor to Adult Romance",
  "description": "禹王與女主童年相識，女主曾保護年幼的禹王，多年後禹王以權勢守護女主。這段關係以恩情為起點、以愛慕為發展，與渣男的利用形成鮮明對比。",
  "tags": [
    "關係",
    "重生復仇",
    "古裝宅鬥",
    "先婚後愛",
    "打臉爽文",
    "惡婆婆",
    "假死陰謀",
    "嫁妝爭奪",
    "智鬥渣男",
    "王爺守護",
    "封棺名場面",
    "族規休妻",
    "養子背叛",
    "白蓮花小三",
    "女主逆襲",
    "皇權加持"
  ],
  "examples": [
    {
      "drama_title": "被假死丈夫和養子聯手滅門？重生歸來她釘棺拒守寡，智鬥渣男復仇，竟陷先婚後愛！《錯嫁君》#重生 #短剧 #最火短剧推荐 #minidrama #古装",
      "video_id": "IygzCYGFVCI",
      "excerpt": "一個小女孩挺身而出保護了我。可惜後來宮裡發生了政變，我被流放到邊疆。等我回來的時候，她已經嫁人了。／她說過要嫁給我，會永遠保護我。",
      "context": "禹王與女主童年相識，女主曾保護年幼的禹王，多年後禹王以權勢守護女主。這段關係以恩情為起點、以愛慕為發展，與渣男的利用形成鮮明對比。"
    }
  ],
  "effectiveness_score": 6,
  "usage_count": 0,
  "created_at": "2026-03-15 15:52:12",
  "updated_at": "2026-03-15 15:52:12"
}