{
  "id": "kb_elements_20260315_155659_0e584a",
  "category": "elements",
  "subcategory": "關係",
  "name": "血緣認親與家族歸屬",
  "name_en": "Blood Reunion and Family Belonging",
  "description": "女主與親生家族的重逢是情感線的核心爽點——不僅是身份的回歸，更是「被愛、被認可、被珍視」的情感需求得到滿足。",
  "tags": [
    "關係",
    "重生",
    "豪門千金",
    "身份互換",
    "復仇逆襲",
    "打臉爽文",
    "渣女受罰",
    "真假千金",
    "家族認親",
    "都市",
    "女性向",
    "快節奏",
    "身份揭露",
    "階級反轉"
  ],
  "examples": [
    {
      "drama_title": "👑Reborn, She Regained Her Identity as the Richest Daughter, the Scumbag Girl Knelt Down Before Her!",
      "video_id": "rAZoM3qsHEc",
      "excerpt": "（字幕資料不足，基於標題推斷）'Richest Daughter' 暗示女主與富豪家族的血緣關係是劇情核心驅動力。",
      "context": "女主與親生家族的重逢是情感線的核心爽點——不僅是身份的回歸，更是「被愛、被認可、被珍視」的情感需求得到滿足。"
    }
  ],
  "effectiveness_score": 6,
  "usage_count": 0,
  "created_at": "2026-03-15 15:56:59",
  "updated_at": "2026-03-15 15:56:59"
}