{
  "id": "kb_elements_20260315_160041_c210c5",
  "category": "elements",
  "subcategory": "關係",
  "name": "包辦婚姻真動心",
  "name_en": "Arranged Marriage Turns to True Love",
  "description": "從被動接受的婚姻安排到主動認知真愛的過程。衝突核心在於：前世的誤解如何在重生後被一一化解，兩人如何從形式上的夫妻變成真正心意相通的伴侶。每一次誤解的消除都是一個小高潮。",
  "tags": [
    "關係",
    "重生",
    "包辦婚姻",
    "隱藏深情",
    "誤解消除",
    "命運改寫",
    "灰姑娘與CEO",
    "婚後戀愛",
    "親子保護",
    "前世今生對比",
    "甜寵爽文",
    "豪門家庭",
    "女主覺醒",
    "幸福結局"
  ],
  "examples": [
    {
      "drama_title": "Reborn, I realized my arranged husband always loved me; we changed kids’ tragic fate, lived happily!",
      "video_id": "EAvRUp2pdK8",
      "excerpt": "（字幕資料不足，基於標題和描述推斷）'arranged husband always loved me' ——包辦婚姻到真愛覺醒的完整關係弧線。#romanticshortchinesedrama 標籤確認浪漫主線。",
      "context": "從被動接受的婚姻安排到主動認知真愛的過程。衝突核心在於：前世的誤解如何在重生後被一一化解，兩人如何從形式上的夫妻變成真正心意相通的伴侶。每一次誤解的消除都是一個小高潮。"
    }
  ],
  "effectiveness_score": 6,
  "usage_count": 0,
  "created_at": "2026-03-15 16:00:41",
  "updated_at": "2026-03-15 16:00:41"
}