{
  "id": "kb_elements_20260315_150140_b00ace",
  "category": "elements",
  "subcategory": "人設",
  "name": "紈絝廢材少爺",
  "name_en": "Spoiled incompetent heir",
  "description": "王元沉迷賭博、懦弱無能，被母親和外人玩弄於股掌之間。他的存在既是喜劇調劑，也是推動股權轉移的關鍵工具人。",
  "tags": [
    "人設",
    "滅門復仇",
    "臥底警察",
    "豪門爭產",
    "身份互換",
    "養女逆襲",
    "整容替身",
    "黑幫犯罪",
    "虐戀情深",
    "遺囑爭奪",
    "俄羅斯輪盤",
    "打臉爽文",
    "多重反轉",
    "毒母控制",
    "子女反噬",
    "商業權謀",
    "臥底暴露"
  ],
  "examples": [
    {
      "drama_title": "申浩男&朱丽岚 | 她是秦家灭门案幸存者，化名寻凶复仇时，遇上深不可测的他。二人在试探中相互吸引[MULTI SUB | FULL]#MiniDrama #精彩大陆短剧",
      "video_id": "oEsKO6n35Gw",
      "excerpt": "CEO Lu please give me one more chance / I'll kneel to you / I'll kowtow CEO Lu / Mom what should I do help me / I can't make a comeback now / You still have your worthless life / You decide for yourself whether to live or die",
      "context": "王元沉迷賭博、懦弱無能，被母親和外人玩弄於股掌之間。他的存在既是喜劇調劑，也是推動股權轉移的關鍵工具人。"
    }
  ],
  "effectiveness_score": 6,
  "usage_count": 0,
  "created_at": "2026-03-15 15:01:40",
  "updated_at": "2026-03-15 15:01:40"
}