{
  "id": "kb_styles_20260315_144439_b9ff3f",
  "category": "styles",
  "subcategory": "",
  "name": "虐戀（先虐後甜/先虐後爽）",
  "name_en": "Angst Romance (Pain-to-Triumph)",
  "description": "前期以背叛和羞辱製造情感痛點（虐），後期以逆襲和真相揭露製造爽點。這種『先苦後甜』的情緒曲線讓最終的payoff更加強烈，因為觀眾已經為主角積累了足夠的同情和憤怒。",
  "tags": [
    "婚禮背叛",
    "CEO總裁",
    "隱忍女主",
    "小三介入",
    "微笑離場",
    "逆襲打臉",
    "爽文",
    "身份反轉",
    "豪門恩怨",
    "都市言情",
    "公開羞辱",
    "從容復仇",
    "全場震驚",
    "先虐後爽",
    "快節奏"
  ],
  "examples": [
    {
      "drama_title": "Wedding day, but CEO registered marriage with his mistress, Girl left smiling, everyone stunned！",
      "video_id": "xbw0jjruAno",
      "excerpt": "前期以背叛和羞辱製造情感痛點（虐），後期以逆襲和真相揭露製造爽點。這種『先苦後甜』的情緒曲線讓最終的payoff更加強烈，因為觀眾已經為主角積累了足夠的同情和憤怒。",
      "context": ""
    },
    {
      "drama_title": "💔Unloved girl no longer tries to please biased family &  makes them cry! KDrama【ENG SUB】【FULL】",
      "video_id": "e3ClWVdySQc",
      "excerpt": "前期以情感虐待建立痛感，後期以反轉和復仇提供快感。情緒特徵是'越虐越深、爽點越強'——前期的痛苦程度決定了後期爽感的強度。這種風格的核心公式是：壓迫深度 × 反擊力度 = 觀眾爽感。",
      "context": ""
    }
  ],
  "effectiveness_score": 6,
  "usage_count": 0,
  "created_at": "2026-03-15 14:44:39",
  "updated_at": "2026-03-15 14:49:01"
}