{
  "id": "kb_dialogues_20260315_162935_ba7e46",
  "category": "dialogues",
  "subcategory": "",
  "name": "威脅型（豪門施壓）",
  "name_en": "Threatening/power play dialogue",
  "description": "利用權力和地位差距進行施壓，製造壓迫感。常見於男主對女主、或配角對女主的對話中。",
  "tags": [
    "製造壓迫感，為後續反擊或化解蓄力",
    "奉子成婚",
    "先婚後愛",
    "霸道總裁",
    "灰姑娘",
    "契約婚姻",
    "口嫌體正直",
    "身世之謎",
    "豪門千金",
    "追妻火葬場",
    "醋意大發",
    "醉酒告白",
    "階級反差",
    "祖孫情深",
    "三角關係",
    "求婚",
    "甜寵短劇",
    "總裁灰姑娘"
  ],
  "examples": [
    {
      "drama_title": "【FULL】一夜縱情，她懷了禁慾大佬的崽，傳聞他矜貴無雙是京圈不可高攀的存在，她以為他娶她是奉子成婚，沒想到他早已愛她至深，非她不可！#短劇 #甜寵 #總裁灰姑娘",
      "video_id": "tDVvBGdgjc4",
      "excerpt": "「Remove the mother and keep the child. Mr. Bo is so cruel」「If you let others spread it. You divorced me. I'll make you leave the house.」「Don't be so proud. I will divorce you sooner or later.」",
      "context": "製造壓迫感，為後續反擊或化解蓄力"
    }
  ],
  "effectiveness_score": 7,
  "usage_count": 0,
  "created_at": "2026-03-15 16:29:35",
  "updated_at": "2026-03-15 16:29:35"
}